fuzeepass/__init__.py
fuzeepass/passx.py
fuzeepass-0.1.1.data/scripts/fp
fuzeepass-0.1.1.data/scripts/fpassx.py
fuzeepass-0.1.1.dist-info/LICENSE
fuzeepass-0.1.1.dist-info/METADATA
fuzeepass-0.1.1.dist-info/WHEEL
fuzeepass-0.1.1.dist-info/top_level.txt
fuzeepass-0.1.1.dist-info/RECORD
