Metadata-Version: 2.1
Name: fuzeepass
Version: 0.1.1
Summary: A command-line fuzzy finder for KeePassX
Home-page: https://github.com/xuta/fuzeepass
Author: Xuta Le
Author-email: xuta.le@gmail.com
License: MIT license
Keywords: fuzeepass
Platform: UNKNOWN
Classifier: Development Status :: 4 - Beta
Classifier: Intended Audience :: Developers
Classifier: License :: OSI Approved :: MIT License
Classifier: Natural Language :: English
Classifier: Programming Language :: Python :: 3.6
Classifier: Programming Language :: Python :: 3.7
Classifier: Programming Language :: Python :: 3.8
Classifier: Programming Language :: Python :: 3.9
Classifier: Topic :: System :: Systems Administration
Requires-Dist: pykeepass (==3.2.1)
Requires-Dist: click (==7.1.2)
